CHANGES.rst
MANIFEST.in
README.rst
setup.py
docs/LICENSE.rst
src/imio/__init__.py
src/imio.ckeditortemplates.egg-info/PKG-INFO
src/imio.ckeditortemplates.egg-info/SOURCES.txt
src/imio.ckeditortemplates.egg-info/dependency_links.txt
src/imio.ckeditortemplates.egg-info/entry_points.txt
src/imio.ckeditortemplates.egg-info/namespace_packages.txt
src/imio.ckeditortemplates.egg-info/not-zip-safe
src/imio.ckeditortemplates.egg-info/requires.txt
src/imio.ckeditortemplates.egg-info/top_level.txt
src/imio/ckeditortemplates/__init__.py
src/imio/ckeditortemplates/configure.zcml
src/imio/ckeditortemplates/interfaces.py
src/imio/ckeditortemplates/profiles.zcml
src/imio/ckeditortemplates/setuphandlers.py
src/imio/ckeditortemplates/testing.py
src/imio/ckeditortemplates/testing.zcml
src/imio/ckeditortemplates/upgrades.py
src/imio/ckeditortemplates/browser/__init__.py
src/imio/ckeditortemplates/browser/configure.zcml
src/imio/ckeditortemplates/browser/imio-ckeditortemplates.css.pt
src/imio/ckeditortemplates/browser/static/adresse.png
src/imio/ckeditortemplates/browser/static/courriel.png
src/imio/ckeditortemplates/browser/static/fax.png
src/imio/ckeditortemplates/browser/static/femme.png
src/imio/ckeditortemplates/browser/static/gsm.png
src/imio/ckeditortemplates/browser/static/homme.png
src/imio/ckeditortemplates/browser/static/horloge.png
src/imio/ckeditortemplates/browser/static/lien.png
src/imio/ckeditortemplates/browser/static/localisation.png
src/imio/ckeditortemplates/browser/static/pdf-1.png
src/imio/ckeditortemplates/browser/static/photo-exemple.jpg
src/imio/ckeditortemplates/browser/static/telephone.png
src/imio/ckeditortemplates/locales/imio.ckeditortemplates.pot
src/imio/ckeditortemplates/profiles/default/browserlayer.xml
src/imio/ckeditortemplates/profiles/default/cssregistry.xml
src/imio/ckeditortemplates/profiles/default/imio.ckeditortemplates.txt
src/imio/ckeditortemplates/profiles/default/metadata.xml
src/imio/ckeditortemplates/profiles/default/propertiestool.xml
src/imio/ckeditortemplates/profiles/testing/imio.ckeditortemplates.txt
src/imio/ckeditortemplates/profiles/testing/metadata.xml
src/imio/ckeditortemplates/profiles/testing/properties.xml
src/imio/ckeditortemplates/tests/__init__.py
src/imio/ckeditortemplates/tests/example.robot
src/imio/ckeditortemplates/tests/test_install.py
src/imio/ckeditortemplates/tests/test_robot.py