Metadata-Version: 2.1
Name: imio.ckeditortemplates
Version: 0.2.6
Summary: Initialisation of CKEditor templates for IMIO
Home-page: http://pypi.python.org/pypi/imio.ckeditortemplates
Author: Benoît Suttor
Author-email: benoit.suttor@imio.be
License: BSD
Keywords: Plone Python
Platform: UNKNOWN
Classifier: Framework :: Plone
Classifier: Programming Language :: Python
Provides-Extra: test
